sortalp/__init__.py
sortalp/function.py
sortapl-1.1.0.dist-info/METADATA
sortapl-1.1.0.dist-info/WHEEL
sortapl-1.1.0.dist-info/top_level.txt
sortapl-1.1.0.dist-info/RECORD
